{
  "id": "heap-siftdown-comparisons",
  "title": "Heap sift-down uses at most 2·height comparisons",
  "statement_informal": "Sift-down in a binary heap uses at most 2·height comparisons.",
  "domain": "sorting",
  "claim_kind": "worst-case",
  "analysis": {
    "case": "worst"
  },
  "targets": [
    "rocq",
    "lean",
    "agda",
    "isabelle"
  ],
  "prompt_template": "prompt-template.md",
  "expected_theorem": "heap_siftdown_comparisons",
  "cost_model": {
    "kind": "func-ops",
    "counts": [
      "comparison"
    ],
    "notes": "Up to two comparisons per level (two children, then larger vs parent) along the descent."
  },
  "references": [
    "Knuth, TAOCP Vol. 3 §5.2.3 — heapsort and sift-down (siftup)."
  ],
  "status": {
    "rocq": "verified",
    "lean": "open",
    "agda": "open",
    "isabelle": "open"
  }
}
